.gitignore
CHANGES.md
LICENSE
README.md
TODO.md
setup.py
tox.ini
examples/arith.asdl
examples/arith.py
examples/toy.asdl
examples/toy.py
iAST.egg-info/PKG-INFO
iAST.egg-info/SOURCES.txt
iAST.egg-info/dependency_links.txt
iAST.egg-info/requires.txt
iAST.egg-info/top_level.txt
iast/__init__.py
iast/node.py
iast/pattern.py
iast/util.py
iast/visitor.py
iast/asdl/Python33.asdl
iast/asdl/Python34.asdl
iast/asdl/__init__.py
iast/asdl/asdl.py
iast/asdl/asdl_test.py
iast/python/__init__.py
iast/python/default.py
iast/python/native.py
iast/python/pynode.py
iast/python/python33.py
iast/python/python34.py
iast/python/pyutil.py
tests/__init__.py
tests/test_node.py
tests/test_pattern.py
tests/test_util.py
tests/test_visitor.py
tests/python/__init__.py
tests/python/test_pynode.py
tests/python/test_pyutil.py