Metadata-Version: 1.1
Name: iAST
Version: 0.2.1
Summary: A library for defining and manipulating ASTs
Home-page: https://github.com/brandjon/iast
Author: Jon Brandvein
Author-email: jon.brandvein@gmail.com
License: MIT License
Platform: UNKNOWN
Classifier: Development Status :: 3 - Alpha
Classifier: Intended Audience :: Developers
Classifier: License :: OSI Approved :: MIT License
Classifier: Programming Language :: Python :: 3
Classifier: Topic :: Software Development :: Libraries :: Python Modules
